pypandoc/__init__.py
pypandoc/pandoc_download.py
pypandoc/handler.py
pypandoc/files/copyright.pandoc
pypandoc/files/pandoc
pypandoc_binary-1.16.2.dist-info/RECORD
pypandoc_binary-1.16.2.dist-info/LICENSE
pypandoc_binary-1.16.2.dist-info/WHEEL
pypandoc_binary-1.16.2.dist-info/top_level.txt
pypandoc_binary-1.16.2.dist-info/METADATA
