Metadata-Version: 2.1
Name: pypandoc_binary
Version: 1.16.2
Summary: Thin wrapper for pandoc.
Home-page: https://github.com/JessicaTegner/pypandoc
Author: b'Juho Veps\xc3\xa4l\xc3\xa4inen; Maintained by Jessica Tegner'
Author-email: jessica@jessicategner.com
License: MIT
Project-URL: Source, https://github.com/JessicaTegner/pypandoc
Project-URL: Tracker, https://github.com/JessicaTegner/pypandoc/issues
Classifier: Development Status :: 4 - Beta
Classifier: Environment :: Console
Classifier: Intended Audience :: Developers
Classifier: Intended Audience :: System Administrators
Classifier: License :: OSI Approved :: MIT License
Classifier: Operating System :: POSIX
Classifier: Programming Language :: Python
Classifier: Topic :: Text Processing
Classifier: Topic :: Text Processing :: Filters
Classifier: Programming Language :: Python :: 3
Classifier: Programming Language :: Python :: 3.7
Classifier: Programming Language :: Python :: 3.8
Classifier: Programming Language :: Python :: 3.9
Classifier: Programming Language :: Python :: 3.10
Classifier: Programming Language :: Python :: 3.11
Classifier: Programming Language :: Python :: 3.12
Classifier: Programming Language :: Python :: 3.13
Classifier: Programming Language :: Python :: 3.14
Classifier: Programming Language :: Python :: 3.15
Classifier: Programming Language :: Python :: Implementation :: CPython
Classifier: Programming Language :: Python :: Implementation :: PyPy
Requires-Python: >=3.7
License-File: LICENSE
